{"pageUpdates":[{"id":"wp-template-burs","title":"Burs Programı","slug":"burs","bodyHtml":"<div class=\"hm-vkd-page-root\">\n<link rel=\"stylesheet\" href=\"https://fonts.googleapis.com/css2?family=Nunito+Sans:wght@400;600;700;800&amp;family=Merriweather:ital,wght@0,400;0,700;1,400&amp;display=swap\">\n<link rel=\"stylesheet\" href=\"https://cdnjs.cloudflare.com/ajax/libs/font-awesome/4.7.0/css/font-awesome.min.css\">\n<style>#content,#MainContent,main#content{max-width:100%!important;padding:0!important;width:100%!important;margin:0!important}\n.page-hero,.page-content,.page__heading,.page__header,.page-header,.page-title{display:none!important}</style>\n<style>.hm-vkd-page-root, .hm-custom-page-body {--r:#8C1A2E;--rd:#6E1222;--rl:rgba(140,26,46,.09);--g:#C9A84C;--gl:rgba(201,168,76,.1);--dk:#0D1117;--dk2:#1C2330;--wh:#FAFAF8;--gr:#F5F2ED;--bd:#E4E0D8;--t1:#1A1F28;--t2:#4A5568;--t3:#718096;--fn:'Nunito Sans',system-ui,sans-serif;--fs:'Merriweather',Georgia,serif;--w:1440px}\n*,*::before,*::after{box-sizing:border-box}\na{text-decoration:none;color:inherit}img{max-width:100%;display:block}ul{list-style:none;padding:0;margin:0}\n.ph{width:100%;background:linear-gradient(150deg,var(--dk) 0%,var(--dk2) 55%,#18060a 100%);padding:72px 40px 60px;position:relative;overflow:hidden}\n.ph::before{content:'';position:absolute;inset:0;background:radial-gradient(ellipse 60% 70% at 80% 50%,rgba(140,26,46,.22) 0%,transparent 65%)}\n.ph-w{max-width:var(--w);margin:0 auto;display:grid;grid-template-columns:1.3fr 1fr;gap:60px;align-items:center;position:relative;z-index:1}\n.ph-ew{display:inline-flex;align-items:center;gap:7px;background:rgba(201,168,76,.12);border:1px solid rgba(201,168,76,.3);color:var(--g);font-size:9.5px;font-weight:700;letter-spacing:2.5px;text-transform:uppercase;padding:6px 14px;border-radius:20px;margin-bottom:18px}\n.ph-h1{font-family:var(--fs);font-size:clamp(1.8rem,3vw,2.8rem);font-weight:700;color:#fff;line-height:1.15;margin-bottom:14px}\n.ph-h1 em{color:var(--g);font-style:italic;display:block}\n.ph-desc{font-size:13.5px;color:rgba(255,255,255,.5);line-height:1.85;max-width:500px}\n.ph-desc strong{color:rgba(255,255,255,.75)}\n.ph-stats{display:grid;grid-template-columns:repeat(3,1fr);gap:1px;background:rgba(255,255,255,.07);border-radius:8px;overflow:hidden;border:1px solid rgba(255,255,255,.07)}\n.ph-si{background:rgba(255,255,255,.04);padding:20px 22px;transition:background .2s}\n.ph-si:hover{background:rgba(255,255,255,.07)}\n.ph-sn{font-size:2rem;font-weight:800;color:var(--g);line-height:1;margin-bottom:4px}\n.ph-sl{font-size:9px;font-weight:700;letter-spacing:1.8px;text-transform:uppercase;color:rgba(255,255,255,.3)}\n.pnav{background:var(--dk2);width:100%}.pnav-in{max-width:var(--w);margin:0 auto;display:flex;overflow-x:auto;scrollbar-width:none}\n.pnav-in::-webkit-scrollbar{display:none}\n.pnav a{display:flex;align-items:center;gap:7px;padding:13px 20px;font-size:10.5px;font-weight:600;color:rgba(255,255,255,.4);text-decoration:none;border-right:1px solid rgba(255,255,255,.06);transition:all .2s;white-space:nowrap;font-family:var(--fn)}\n.pnav a:hover,.pnav a.on{color:var(--g);background:rgba(201,168,76,.06)}\n.pbc{max-width:var(--w);margin:0 auto;padding:13px 40px;display:flex;align-items:center;gap:6px;font-size:11px;color:var(--t3);border-bottom:1px solid var(--bd)}\n.pbc a{color:var(--r);text-decoration:none;font-weight:600}\n.sec{width:100%;padding:48px 40px}.sec:nth-child(even){background:var(--gr)}\n.sec-w{max-width:var(--w);margin:0 auto}\n.sec-hd{margin-bottom:26px;padding-bottom:16px;border-bottom:2px solid var(--bd)}\n.badge{display:inline-flex;align-items:center;gap:5px;font-size:8.5px;font-weight:700;letter-spacing:1.5px;text-transform:uppercase;padding:3px 9px;border-radius:20px;margin-bottom:9px;border:1px solid}\n.badge.r{background:var(--rl);color:var(--r);border-color:rgba(140,26,46,.2)}.badge.g{background:var(--gl);color:#7a5a00;border-color:rgba(201,168,76,.3)}.badge.b{background:#EFF6FF;color:#1D4ED8;border-color:#BFDBFE}.badge.gr{background:#F0FDF4;color:#15803D;border-color:#BBF7D0}.badge.p{background:#F5F3FF;color:#6D28D9;border-color:#DDD6FE}\n.sec-title{font-family:var(--fs);font-size:1.5rem;font-weight:700;color:var(--t1);margin-bottom:6px}\n.sec-sub{font-size:13px;color:var(--t3);line-height:1.7;max-width:680px}\n.grid{display:grid;gap:14px}.g4{grid-template-columns:repeat(4,1fr)}.g3{grid-template-columns:repeat(3,1fr)}.g2{grid-template-columns:repeat(2,1fr)}\n.card{background:#fff;border:1px solid var(--bd);border-radius:8px;overflow:hidden;display:flex;flex-direction:column;transition:all .22s}\n.card:hover{box-shadow:0 8px 32px rgba(0,0,0,.09);transform:translateY(-2px)}\n.card-st{height:4px}.card-st.r{background:linear-gradient(90deg,var(--r),#c0392b)}.card-st.g{background:linear-gradient(90deg,#15803D,#22c55e)}.card-st.b{background:linear-gradient(90deg,#1D4ED8,#60a5fa)}.card-st.p{background:linear-gradient(90deg,#6D28D9,#8b5cf6)}.card-st.gold{background:linear-gradient(90deg,var(--g),#e0a030)}.card-st.t{background:linear-gradient(90deg,#0a5c6e,#0e9aa0)}.card-st.dk{background:linear-gradient(90deg,#0f2c5c,#1d4ed8)}\n.card-body{padding:22px 22px 16px;flex:1;display:flex;flex-direction:column;gap:10px}\n.card-icon{width:52px;height:52px;border-radius:10px;display:flex;align-items:center;justify-content:center;font-size:1.4rem;margin-bottom:6px}\n.card-icon.r{background:var(--rl);color:var(--r)}.card-icon.g{background:#F0FDF4;color:#15803D}.card-icon.b{background:#EFF6FF;color:#1D4ED8}.card-icon.p{background:#F5F3FF;color:#6D28D9}.card-icon.gold{background:var(--gl);color:#7a5a00}.card-icon.t{background:#ECFEFF;color:#0a5c6e}.card-icon.dk{background:#EFF6FF;color:#0f2c5c}\n.card-title{font-family:var(--fs);font-size:1rem;font-weight:700;color:var(--t1);line-height:1.3}\n.card-desc{font-size:12px;color:var(--t2);line-height:1.75;flex:1}\n.card-list{list-style:none;padding:0;margin:6px 0 0;display:flex;flex-direction:column;gap:4px}\n.card-list li{font-size:11px;color:var(--t2);display:flex;gap:7px;line-height:1.5}\n.card-list li::before{content:\"✓\";color:var(--r);font-weight:700;flex-shrink:0}\n.card-foot{padding:10px 20px;border-top:1px solid var(--bd);background:var(--gr);display:flex;align-items:center;justify-content:space-between}\n.card-lbl{font-size:9px;font-weight:700;letter-spacing:.5px;text-transform:uppercase;color:var(--t3)}\n.card-lnk{font-size:10.5px;font-weight:700;color:var(--r);text-decoration:none}\n.ctaband{background:var(--r);padding:40px;width:100%}\n.ctaband-w{max-width:var(--w);margin:0 auto;display:flex;align-items:center;justify-content:space-between;gap:32px;flex-wrap:wrap}\n.ctaband-text h3{font-family:var(--fs);font-size:1.3rem;font-weight:700;color:#fff;margin-bottom:6px}\n.ctaband-text p{font-size:13px;color:rgba(255,255,255,.65);line-height:1.6}\n.ctabtns{display:flex;gap:10px;flex-wrap:wrap}\n.pbtn{display:inline-flex;align-items:center;gap:7px;padding:11px 22px;border-radius:4px;font-size:12px;font-weight:700;text-decoration:none;font-family:var(--fn);transition:all .2s}\n.pbtn.wh{background:#fff;color:var(--r)}.pbtn.wh:hover{background:#f5e8e8}\n.pbtn.ol{background:transparent;color:#fff;border:1.5px solid rgba(255,255,255,.45)}.pbtn.ol:hover{background:rgba(255,255,255,.1)}\n.qband{background:linear-gradient(135deg,var(--dk),var(--dk2));border-top:3px solid var(--g);padding:52px 40px;text-align:center;width:100%}\n.qband-w{max-width:var(--w);margin:0 auto}\n.qband-text{font-family:var(--fs);font-size:clamp(1.2rem,2vw,1.8rem);font-style:italic;color:#fff;max-width:760px;margin:0 auto 14px;line-height:1.5}\n.qband-text em{color:var(--g)}\n.qband-src{font-size:10px;font-weight:700;letter-spacing:2px;text-transform:uppercase;color:rgba(255,255,255,.35)}\n@media(max-width:1200px){.g4{grid-template-columns:repeat(2,1fr)}}\n@media(max-width:860px){.g3,.g2{grid-template-columns:repeat(2,1fr)}.ph-w{grid-template-columns:1fr;gap:32px}.sec,.ph,.ctaband,.qband{padding:40px 24px}.pbc{padding:12px 24px}}\n@media(max-width:540px){.g4,.g3,.g2{grid-template-columns:1fr}}\n\n.ph{background:linear-gradient(150deg,#0a1628 0%,#0f2244 55%,#1a0810 100%) !important}\n.ph::before{background:radial-gradient(ellipse 60% 70% at 80% 50%,rgba(29,78,216,.2) 0%,transparent 65%) !important}\n.basvuru-box{background:#fff;border:1px solid var(--bd);border-radius:8px;overflow:hidden;max-width:800px;margin:0 auto}\n.basvuru-head{background:linear-gradient(135deg,#1D4ED8,#1e3a8a);padding:22px 28px}\n.basvuru-head h3{font-family:var(--fs);font-size:1.1rem;font-weight:700;color:#fff;margin-bottom:4px}\n.basvuru-head p{font-size:12px;color:rgba(255,255,255,.6)}\n.basvuru-body{padding:28px}\n.fg{display:flex;flex-direction:column;gap:5px;margin-bottom:16px}\n.fg label{font-size:10px;font-weight:700;text-transform:uppercase;letter-spacing:.5px;color:var(--t2)}\n.fg input,.fg select,.fg textarea{border:1.5px solid var(--bd);border-radius:6px;padding:10px 14px;font-size:13px;font-family:var(--fn);outline:none;width:100%}\n.fg input:focus,.fg select:focus,.fg textarea:focus{border-color:#1D4ED8}\n.fg-row{display:grid;grid-template-columns:1fr 1fr;gap:14px}\n.fg-submit{display:block;width:100%;background:#1D4ED8;color:#fff;border:none;border-radius:6px;padding:13px;font-size:14px;font-weight:700;cursor:pointer;font-family:var(--fn);margin-top:8px}\n.fg-submit:hover{background:#1e3a8a}\n.pw{font-family:var(--fn);background:var(--wh);color:var(--t1)}\n@media(max-width:860px){.fg-row{grid-template-columns:1fr}}</style>\n\n<div class=\"pw\">\n\n\n<div class=\"ph\">\n  <div class=\"ph-w\">\n    <div>\n      <div class=\"ph-ew\">🎓 Eğitim &amp; Burs Programı</div>\n      <h1 class=\"ph-h1\">Kahraman Çocuklarına<em>Eğitim Desteği</em></h1>\n      <p class=\"ph-desc\">Vatan kahramanlarımızın çocuklarına yönelik <strong>burs programları, akademik mentorluk, sosyal gelişim projeleri ve uluslararası öğrenci değişim programları</strong> sunuyoruz. Kültürel etkileşim ve küresel vizyon hedefimizin merkezindedir.</p>\n    </div>\n    <div>\n      <div class=\"ph-stats\">\n        <div class=\"ph-si\"><div class=\"ph-sn\">5</div><div class=\"ph-sl\">Türk Devleti</div></div>\n        <div class=\"ph-si\"><div class=\"ph-sn\">13</div><div class=\"ph-sl\">Ülke Ağı</div></div>\n        <div class=\"ph-si\"><div class=\"ph-sn\">3</div><div class=\"ph-sl\">Program Türü</div></div>\n        <div class=\"ph-si\"><div class=\"ph-sn\">🎓</div><div class=\"ph-sl\">Lisans & Lisansüstü</div></div>\n        <div class=\"ph-si\"><div class=\"ph-sn\">🌍</div><div class=\"ph-sl\">Yurt Dışı Burs</div></div>\n        <div class=\"ph-si\"><div class=\"ph-sn\">100%</div><div class=\"ph-sl\">Ücretsiz</div></div>\n      </div>\n    </div>\n  </div>\n</div>\n\n\n<div class=\"pnav\"><div class=\"pnav-in\">\n  <a href=\"/burs\" class=\"on\">🎓 Burs &amp; Eğitim</a>\n  <a href=\"/insani-yardim\">🔴 İnsani Yardım</a>\n  <a href=\"/etkinlikler\">🟡 Etkinlikler</a>\n  <a href=\"/isbirligi\">📋 Tüm Programlar</a>\n  <a href=\"/bagis\">💝 Bağış</a>\n  <a href=\"/iletisim\">📩 Başvur</a>\n</div></div>\n<div class=\"pbc\"><a href=\"/\">Ana Sayfa</a> › <a href=\"/isbirligi\">İşbirliği</a> › <span>Burs &amp; Eğitim Programları</span></div>\n\n\n<div class=\"sec\">\n  <div class=\"sec-w\">\n    <div class=\"sec-hd\">\n      <div class=\"badge b\">🎓 Program Türleri</div>\n      <div class=\"sec-title\">Eğitim Destek Programlarımız</div>\n      <div class=\"sec-sub\">Şehit ve gazi ailelerinin çocuklarına yönelik üç temel program alanı — lisans, lisansüstü ve öğrenci değişimi.</div>\n    </div>\n    <div class=\"grid g3\">\n      <div class=\"card\">\n        <div class=\"card-st b\"></div>\n        <div class=\"card-body\">\n          <div class=\"card-icon b\"><i class=\"fa fa-graduation-cap\"></i></div>\n          <div class=\"card-title\">Lisans &amp; Lisansüstü Burs</div>\n          <div class=\"card-desc\">Türkiye, Azerbaycan, Kazakistan, Kırgızistan, Özbekistan üniversitelerinde eğitim gören şehit ve gazi çocuklarına yönelik doğrudan burs desteği.</div>\n          <ul class=\"card-list\">\n            <li>Yıllık eğitim ödemesi desteği</li>\n            <li>Kırtasiye ve yaşam gideri katkısı</li>\n            <li>Akademik başarı teşvik ödülleri</li>\n            <li>Yurt dışı lisansüstü burs seçeneği</li>\n          </ul>\n        </div>\n        <div class=\"card-foot\"><span class=\"card-lbl\">5 Türk Devleti</span><a href=\"#basvuru\" class=\"card-lnk\">Başvur →</a></div>\n      </div>\n      <div class=\"card\">\n        <div class=\"card-st b\"></div>\n        <div class=\"card-body\">\n          <div class=\"card-icon b\"><i class=\"fa fa-exchange\"></i></div>\n          <div class=\"card-title\">Öğrenci Değişim Programları</div>\n          <div class=\"card-desc\">Vatan kahramanlarımızın çocuklarına yönelik uluslararası öğrenci değişim projeleriyle kültürel etkileşim ve küresel vizyon destekleniyor. TDT Orhun Programı entegrasyonu.</div>\n          <ul class=\"card-list\">\n            <li>Türk dünyasında öğrenci plasman</li>\n            <li>Macaristan ve Balkan üniversiteleri</li>\n            <li>Dil eğitimi ve kültürel oryantasyon</li>\n            <li>Gazi ailesi öncelikli kontenjan</li>\n          </ul>\n        </div>\n        <div class=\"card-foot\"><span class=\"card-lbl\">TDT Orhun Programı</span><a href=\"#basvuru\" class=\"card-lnk\">Başvur →</a></div>\n      </div>\n      <div class=\"card\">\n        <div class=\"card-st b\"></div>\n        <div class=\"card-body\">\n          <div class=\"card-icon b\"><i class=\"fa fa-user-graduate\" style=\"font-size:1.2rem\"></i></div>\n          <div class=\"card-title\">Akademik Mentorluk Programı</div>\n          <div class=\"card-desc\">Eğitim hayatlarını güçlendirmek amacıyla akademik mentorluk ve sosyal gelişim projeleri. Kariyer danışmanlığı ve liderlik geliştirme.</div>\n          <ul class=\"card-list\">\n            <li>Birebir mentor eşleştirme sistemi</li>\n            <li>Kariyer planlaması ve danışmanlık</li>\n            <li>Liderlik ve kişisel gelişim atölyeleri</li>\n            <li>Alumni ağı — mezun öğrenci topluluğu</li>\n          </ul>\n        </div>\n        <div class=\"card-foot\"><span class=\"card-lbl\">Mentorluk Ağı</span><a href=\"#basvuru\" class=\"card-lnk\">Başvur →</a></div>\n      </div>\n    </div>\n  </div>\n</div>\n\n\n<div class=\"sec\">\n  <div class=\"sec-w\">\n    <div class=\"sec-hd\">\n      <div class=\"badge g\">🌍 Değişim Ağı</div>\n      <div class=\"sec-title\">Hangi Ülkelerde Program Var?</div>\n      <div class=\"sec-sub\">Türk devletleri ve dost ülkelerdeki üniversiteler ile imzalanan protokoller çerçevesinde öğrenci plasman hizmeti.</div>\n    </div>\n    <div class=\"grid g4\">\n      <div class=\"card\"><div class=\"card-st gold\"></div><div class=\"card-body\"><div style=\"font-size:2rem;margin-bottom:10px\">🇹🇷</div><div class=\"card-title\">Türkiye</div><div class=\"card-desc\">Ankara, İstanbul, İzmir başta olmak üzere 81 ilde devlet ve vakıf üniversitelerinde burs ve plasman imkânı.</div></div></div>\n      <div class=\"card\"><div class=\"card-st gold\"></div><div class=\"card-body\"><div style=\"font-size:2rem;margin-bottom:10px\">🇦🇿</div><div class=\"card-title\">Azerbaycan</div><div class=\"card-desc\">Bakü Devlet Üniversitesi ve Azerbaycan Teknik Üniversitesi'nde öğrenci değişim kontenjanı.</div></div></div>\n      <div class=\"card\"><div class=\"card-st gold\"></div><div class=\"card-body\"><div style=\"font-size:2rem;margin-bottom:10px\">🇰🇿</div><div class=\"card-title\">Kazakistan</div><div class=\"card-desc\">Astana ve Almatı'daki önde gelen üniversitelerde akademik değişim programı. Türk Akademisi iş birliği.</div></div></div>\n      <div class=\"card\"><div class=\"card-st gold\"></div><div class=\"card-body\"><div style=\"font-size:2rem;margin-bottom:10px\">🇰🇬</div><div class=\"card-title\">Kırgızistan</div><div class=\"card-desc\">Bişkek Manas Üniversitesi'nde Türkçe eğitim veren bölümlerde öğrenci değişimi.</div></div></div>\n      <div class=\"card\"><div class=\"card-st gold\"></div><div class=\"card-body\"><div style=\"font-size:2rem;margin-bottom:10px\">🇺🇿</div><div class=\"card-title\">Özbekistan</div><div class=\"card-desc\">Taşkent Türk-Özbek Eğitim Üniversitesi ve Samarkand devlet üniversitelerinde burs imkânı.</div></div></div>\n      <div class=\"card\"><div class=\"card-st gold\"></div><div class=\"card-body\"><div style=\"font-size:2rem;margin-bottom:10px\">🇭🇺</div><div class=\"card-title\">Macaristan</div><div class=\"card-desc\">Budapeşte üniversitelerinde yüksek lisans ve doktora burs programı. AB ortamlı akademik deneyim.</div></div></div>\n      <div class=\"card\"><div class=\"card-st gold\"></div><div class=\"card-body\"><div style=\"font-size:2rem;margin-bottom:10px\">🇧🇦</div><div class=\"card-title\">Bosna Hersek</div><div class=\"card-desc\">Saraybosna Üniversitesi'nde Balkan perspektifli sosyal bilimler alanında değişim programı.</div></div></div>\n      <div class=\"card\"><div class=\"card-st gold\"></div><div class=\"card-body\"><div style=\"font-size:2rem;margin-bottom:10px\">🇵🇰</div><div class=\"card-title\">Pakistan</div><div class=\"card-desc\">İslamabad ve Karaçi üniversitelerinde mühendislik ve tıp alanlarında öğrenci değişim imkânı.</div></div></div>\n    </div>\n  </div>\n</div>\n\n\n<div class=\"sec\" id=\"basvuru\">\n  <div class=\"sec-w\">\n    <div class=\"sec-hd\">\n      <div class=\"badge r\">📝 Başvuru</div>\n      <div class=\"sec-title\">Burs Başvurusu Yapın</div>\n      <div class=\"sec-sub\">Şehit veya gazi ailesine mensup olduğunuzu belgeleyerek başvurunuzu iletebilirsiniz.</div>\n    </div>\n    <div class=\"basvuru-box\">\n      <div class=\"basvuru-head\">\n        <h3>🎓 Burs &amp; Değişim Başvuru Formu</h3>\n        <p>Formunuz en kısa sürede incelenerek geri dönüş yapılacaktır</p>\n      </div>\n      <div class=\"basvuru-body\">\n        <div class=\"fg-row\">\n          <div class=\"fg\"><label>Ad Soyad *</label><input type=\"text\" placeholder=\"Adınız Soyadınız\"></div>\n          <div class=\"fg\"><label>T.C. Kimlik No *</label><input type=\"text\" placeholder=\"___________\"></div>\n        </div>\n        <div class=\"fg-row\">\n          <div class=\"fg\"><label>E-posta *</label><input type=\"email\" placeholder=\"ornek@mail.com\"></div>\n          <div class=\"fg\"><label>Telefon *</label><input type=\"tel\" placeholder=\"+90 5__ ___ __ __\"></div>\n        </div>\n        <div class=\"fg-row\">\n          <div class=\"fg\"><label>Başvuru Türü *</label>\n            <select>\n              <option value>Seçiniz...</option>\n              <option>Lisans Bursu</option>\n              <option>Lisansüstü Bursu</option>\n              <option>Öğrenci Değişim Programı</option>\n              <option>Akademik Mentorluk</option>\n            </select>\n          </div>\n          <div class=\"fg\"><label>Şehit/Gazi Yakınlığı *</label>\n            <select>\n              <option value>Seçiniz...</option>\n              <option>Şehidin Çocuğu</option>\n              <option>Şehidin Eşi</option>\n              <option>Gazinin Çocuğu</option>\n              <option>Gazinin Kendisi</option>\n            </select>\n          </div>\n        </div>\n        <div class=\"fg\"><label>Başvuru Notunuz</label><textarea rows=\"4\" placeholder=\"Eğitim durumunuz, hedefleriniz ve destekten nasıl yararlanacağınızı kısaca açıklayın...\"></textarea></div>\n        <button class=\"fg-submit\" type=\"button\">{this.textContent='Başvur →';this.style.background='#1D4ED8'},3000)\">Başvur →</button>\n      </div>\n    </div>\n  </div>\n</div>\n\n\n<div class=\"ctaband\">\n  <div class=\"ctaband-w\">\n    <div class=\"ctaband-text\"><h3>Eğitim Desteklerimizi Güçlendirin</h3><p>Her burs katkısı bir kahraman çocuğunun geleceğine yatırımdır · Stripe güvenceli · 501(c)(3) onaylı</p></div>\n    <div class=\"ctabtns\">\n      <a href=\"/bagis\" class=\"pbtn wh\">💝 Bağış Yap</a>\n      <a href=\"/iletisim\" class=\"pbtn ol\">📩 İletişim</a>\n    </div>\n  </div>\n</div>\n\n</div>\n</div>","enabled":true,"fullWidth":false,"importSource":"wordpress-template","sourceName":"page-burs.php","importedAt":"2026-05-22T18:04:21.008Z"},{"id":"wp-template-canakkale-savasi","title":"Çanakkale Savaşı","slug":"canakkale-savasi","bodyHtml":"<div class=\"hm-vkd-page-root\">\n<link rel=\"stylesheet\" href=\"https://fonts.googleapis.com/css2?family=Nunito+Sans:wght@400;600;700;800&amp;family=Merriweather:ital,wght@0,400;0,700;1,400&amp;display=swap\">\n<style>.hm-vkd-page-root, .hm-custom-page-body {--r:#8C1A2E;--rd:#6E1222;--g:#C9A84C;--dk:#0D1117;--dk2:#1C2330;--wh:#FAFAF8;--gr:#F5F2ED;--bd:#E4E0D8;--t1:#1A1F28;--t2:#4A5568;--t3:#718096;--fn:'Nunito Sans',system-ui,sans-serif;--fs:'Merriweather',Georgia,serif;--w:1440px}\n*{box-sizing:border-box}\n.pw{font-family:var(--fn);background:var(--wh);color:var(--t1)}\n#content,main{max-width:100%!important;padding:0!important;width:100%!important;margin:0!important}\n.ph{width:100%;background:linear-gradient(150deg,#050709 0%,#0D1117 45%,#1a0a10 100%);padding:80px 40px 64px;position:relative;overflow:hidden}\n.ph::before{content:'';position:absolute;inset:0;background:radial-gradient(ellipse at 30% 60%,rgba(140,26,46,.18) 0%,transparent 60%)}\n.ph-w{max-width:var(--w);margin:0 auto;display:grid;grid-template-columns:1.2fr 1fr;gap:60px;align-items:center;position:relative;z-index:1}\n.ph-ew{display:inline-flex;align-items:center;gap:8px;background:rgba(140,26,46,.2);border:1px solid rgba(140,26,46,.4);color:#e87a8a;font-size:9.5px;font-weight:700;letter-spacing:2.5px;text-transform:uppercase;padding:6px 14px;border-radius:20px;margin-bottom:18px}\n.ph-h1{font-family:var(--fs);font-size:clamp(2rem,3.5vw,3rem);font-weight:700;color:#fff;line-height:1.12;margin-bottom:14px}\n.ph-h1 em{color:var(--g);font-style:italic;display:block}\n.ph-desc{font-size:13.5px;color:rgba(255,255,255,.55);line-height:1.85;max-width:520px;margin-bottom:10px}\n.ph-quote{background:rgba(140,26,46,.15);border-left:3px solid var(--r);padding:16px 20px;border-radius:0 6px 6px 0;margin-top:20px;font-family:var(--fs);font-size:13px;font-style:italic;color:rgba(255,255,255,.8);line-height:1.7}\n.ph-stats{display:grid;grid-template-columns:repeat(2,1fr);gap:10px}\n.ph-stat{background:rgba(255,255,255,.05);border:1px solid rgba(255,255,255,.08);border-radius:6px;padding:16px 18px;text-align:center}\n.ph-stat-num{font-size:1.5rem;font-weight:800;color:var(--g);line-height:1;margin-bottom:4px}\n.ph-stat-lbl{font-size:9px;font-weight:700;letter-spacing:1.5px;text-transform:uppercase;color:rgba(255,255,255,.35)}\n.sec{width:100%;padding:64px 40px}\n.sec.alt{background:var(--gr)}\n.sec.dark{background:var(--dk);padding:64px 40px}\n.sec-w{max-width:var(--w);margin:0 auto}\n.badge{display:inline-block;padding:4px 14px;border-radius:20px;font-size:9.5px;font-weight:800;text-transform:uppercase;letter-spacing:1.5px;margin-bottom:10px}\n.badge.g{background:rgba(201,168,76,.1);color:#7a5a00;border:1px solid rgba(201,168,76,.3)}\n.badge.r{background:rgba(140,26,46,.08);color:var(--r);border:1px solid rgba(140,26,46,.15)}\n.badge.w{background:rgba(255,255,255,.08);color:rgba(255,255,255,.7);border:1px solid rgba(255,255,255,.15)}\n.sec-title{font-family:var(--fs);font-size:1.9rem;font-weight:700;color:var(--t1);margin-bottom:10px}\n.sec-title.wh{color:#fff}\n.sec-sub{font-size:14px;color:var(--t3);line-height:1.75;max-width:760px;margin-bottom:32px}\n.sec-sub.wh{color:rgba(255,255,255,.5)}\n.g2{display:grid;grid-template-columns:repeat(2,1fr);gap:24px}\n.g3{display:grid;grid-template-columns:repeat(3,1fr);gap:20px}\n.g4{display:grid;grid-template-columns:repeat(4,1fr);gap:16px}\n.card{background:#fff;border:1px solid var(--bd);border-radius:10px;padding:24px;transition:all .22s;position:relative;overflow:hidden}\n.card::before{content:'';position:absolute;top:0;left:0;right:0;height:4px;background:linear-gradient(90deg,var(--r),var(--g))}\n.card:hover{box-shadow:0 8px 28px rgba(0,0,0,.08);transform:translateY(-3px)}\n.tl{display:flex;flex-direction:column;position:relative}\n.tl::before{content:'';position:absolute;left:28px;top:0;bottom:0;width:2px;background:var(--bd)}\n.tl-item{display:flex;gap:22px;align-items:flex-start;padding-bottom:28px}\n.tl-dot{width:56px;height:56px;border-radius:50%;background:var(--r);border:3px solid #fff;display:flex;align-items:center;justify-content:center;font-size:1rem;flex-shrink:0;position:relative;z-index:1;box-shadow:0 0 0 4px var(--bd)}\n.tl-body{padding:8px 0 0;flex:1}\n.tl-date{font-size:10px;font-weight:800;letter-spacing:2px;text-transform:uppercase;color:var(--r);margin-bottom:4px}\n.tl-title{font-family:var(--fs);font-size:1rem;font-weight:700;color:var(--t1);margin-bottom:6px}\n.tl-desc{font-size:12.5px;color:var(--t2);line-height:1.8}\n.commander-grid{display:grid;grid-template-columns:repeat(3,1fr);gap:20px}\n.cmd-card{background:rgba(255,255,255,.04);border:1px solid rgba(255,255,255,.08);border-radius:10px;padding:24px;text-align:center}\n.cmd-flag{font-size:2.5rem;margin-bottom:12px}\n.cmd-name{font-family:var(--fs);font-size:.95rem;font-weight:700;color:#fff;margin-bottom:4px}\n.cmd-title{font-size:10.5px;font-weight:700;letter-spacing:1px;text-transform:uppercase;color:var(--g);margin-bottom:10px}\n.cmd-desc{font-size:11.5px;color:rgba(255,255,255,.5);line-height:1.65}\n.anma-card{background:#fff;border:1px solid var(--bd);border-radius:10px;padding:24px;display:flex;gap:20px;align-items:flex-start}\n.anma-date{background:var(--r);color:#fff;border-radius:6px;padding:12px 16px;text-align:center;flex-shrink:0;min-width:72px}\n.anma-day{font-size:1.6rem;font-weight:800;line-height:1}\n.anma-month{font-size:9px;font-weight:700;letter-spacing:1.5px;text-transform:uppercase;margin-top:2px}\n.anma-body h4{font-family:var(--fs);font-size:1rem;font-weight:700;color:var(--t1);margin-bottom:6px}\n.anma-body p{font-size:12.5px;color:var(--t2);line-height:1.75}\n.cta-band{background:linear-gradient(135deg,var(--r),var(--rd));padding:52px 40px;width:100%}\n.cta-w{max-width:var(--w);margin:0 auto;display:flex;align-items:center;justify-content:space-between;gap:32px;flex-wrap:wrap}\n.cta-text h3{font-family:var(--fs);font-size:1.4rem;font-weight:700;color:#fff;margin-bottom:8px}\n.cta-text p{font-size:13px;color:rgba(255,255,255,.65);line-height:1.6}\n.btn-wh{display:inline-flex;align-items:center;gap:7px;padding:11px 22px;background:#fff;color:var(--r);border-radius:4px;font-size:12px;font-weight:700;text-decoration:none}\n.btn-ol{display:inline-flex;align-items:center;gap:7px;padding:11px 22px;background:transparent;color:#fff;border:1.5px solid rgba(255,255,255,.4);border-radius:4px;font-size:12px;font-weight:700;text-decoration:none}\n@media(max-width:1024px){.g4{grid-template-columns:repeat(2,1fr)}.commander-grid{grid-template-columns:repeat(2,1fr)}}\n@media(max-width:768px){.ph-w,.g3,.g2{grid-template-columns:1fr}.sec,.ph,.cta-band{padding:48px 24px}.ph-stats{grid-template-columns:repeat(2,1fr)}}</style>\n\n<div class=\"pw\">\n\n\n<div class=\"ph\">\n  <div class=\"ph-w\">\n    <div>\n      <div class=\"ph-ew\">⚔️ Savaşlar · Çanakkale</div>\n      <h1 class=\"ph-h1\">Çanakkale Savaşları<em>1915 — Ölmek İçin Emir</em></h1>\n      <p class=\"ph-desc\">Tarihin en çetin savunma muharebelerinden biri. Çanakkale Cephesi'nde Türk askeri, ezici bir üstünlüğe sahip İtilaf kuvvetlerini sekiz ay boyunca durdurmayı başardı ve tarihin akışını değiştirdi.</p>\n      <div class=\"ph-quote\">\"Size taarruzu değil, ölmeyi emrediyorum. Bize taarruz edecek olan düşmana karşı geçecek zaman zarfında, başka kuvvetler ve kumandanlar mevziimize gelebilir.\"<br><span style=\"font-size:10px;font-weight:700;letter-spacing:1px;text-transform:uppercase;opacity:.6;margin-top:8px;display:block\">— Mustafa Kemal, Arıburnu, 1915</span></div>\n    </div>\n    <div class=\"ph-stats\">\n      <div class=\"ph-stat\"><div class=\"ph-stat-num\">250.000+</div><div class=\"ph-stat-lbl\">Türk Şehit ve Yaralı</div></div>\n      <div class=\"ph-stat\"><div class=\"ph-stat-num\">8 Ay</div><div class=\"ph-stat-lbl\">Cephe Süresi</div></div>\n      <div class=\"ph-stat\"><div class=\"ph-stat-num\">500.000+</div><div class=\"ph-stat-lbl\">İtilaf Kaybı</div></div>\n      <div class=\"ph-stat\"><div class=\"ph-stat-num\">18 Mart</div><div class=\"ph-stat-lbl\">Zafer Günü</div></div>\n    </div>\n  </div>\n</div>\n\n\n<div class=\"sec\">\n  <div class=\"sec-w\">\n    <div class=\"g2\">\n      <div>\n        <div class=\"badge r\">Savaşın Önemi</div>\n        <h2 class=\"sec-title\">Çanakkale Neden Önemlidir?</h2>\n        <p style=\"font-size:13.5px;color:var(--t2);line-height:1.9;margin-bottom:14px\">Çanakkale Savaşları (Şubat 1915 – Ocak 1916), I. Dünya Savaşı'nın en kritik cephelerinden birini oluşturur. İngiltere ve Fransa öncülüğündeki İtilaf devletleri, İstanbul Boğazı'nı geçerek Osmanlı İmparatorluğu'nu savaş dışı bırakmayı ve Rusya'ya ikmal yolu açmayı hedefliyordu.</p>\n        <p style=\"font-size:13.5px;color:var(--t2);line-height:1.9;margin-bottom:14px\">Türk ordusu, sayı ve teçhizat bakımından çok üstün bir düşmana karşı sekiz ay boyunca yarımadayı savundu. Bu savunma yalnızca askeri bir zafer değil; bir milletin yeniden doğuş destanı oldu. Mustafa Kemal'in burada kazandığı ün, ileride Millî Mücadele'yi örgütleyecek liderin filizlendiği toprak oldu.</p>\n        <p style=\"font-size:13.5px;color:var(--t2);line-height:1.9\">Çanakkale zaferi; İtilaf devletlerinin doğu stratejisini çökertti, Rusya'nın ikmal yolunu kapattı ve Osmanlı'nın çöküşünü en az bir yıl geciktirdi. Bugün hem Türkiye hem de ANZAC ülkeleri (Avustralya ve Yeni Zelanda) bu muharebe alanlarını saygıyla anmaktadır.</p>\n      </div>\n      <div>\n        <div class=\"badge g\">Temel Bilgiler</div>\n        <h2 class=\"sec-title\">Savaşın Künyesi</h2>\n        \n        \n        \n      </div>\n    </div>\n  </div>\n</div>\n\n\n<div class=\"sec alt\">\n  <div class=\"sec-w\">\n    <div class=\"badge r\">Kronoloji</div>\n    <h2 class=\"sec-title\">Savaşın Seyri</h2>\n    <p class=\"sec-sub\">Çanakkale Savaşları'nın aylara göre gelişimi ve dönüm noktaları.</p>\n    <div class=\"g2\">\n      <div class=\"tl\">\n        \n        <div class=\"tl-item\">\n          <div class=\"tl-dot\"></div>\n          <div class=\"tl-body\">\n            <div class=\"tl-date\"></div>\n            <div class=\"tl-title\"></div>\n            \n          </div>\n        </div>\n        \n      </div>\n      <div class=\"tl\">\n        \n        <div class=\"tl-item\">\n          <div class=\"tl-dot\"></div>\n          <div class=\"tl-body\">\n            <div class=\"tl-date\"></div>\n            <div class=\"tl-title\"></div>\n            \n          </div>\n        </div>\n        \n      </div>\n    </div>\n  </div>\n</div>\n\n\n<div class=\"sec\">\n  <div class=\"sec-w\">\n    <div class=\"badge g\">Başlıca Muharebeler</div>\n    <h2 class=\"sec-title\">Cephenin Kritik Noktaları</h2>\n    <div class=\"g3\">\n      \n      <div class=\"card\">\n        \n        \n        <h4 style=\"font-family:var(--fs);font-size:.95rem;font-weight:700;color:var(--t1);margin-bottom:10px\"></h4>\n        \n      </div>\n      \n    </div>\n  </div>\n</div>\n\n\n<div class=\"sec dark\">\n  <div class=\"sec-w\">\n    <div class=\"badge w\">Komutanlar</div>\n    <h2 class=\"sec-title wh\">Cephenin Önemli İsimleri</h2>\n    <p class=\"sec-sub wh\">Çanakkale Savaşları'nda tarihe geçen komutanlar.</p>\n    <div class=\"commander-grid\">\n      \n      <div class=\"cmd-card\">\n        <div class=\"cmd-flag\"></div>\n        <div class=\"cmd-name\"></div>\n        <div class=\"cmd-title\"></div>\n        \n      </div>\n      \n    </div>\n  </div>\n</div>\n\n\n<div class=\"sec\">\n  <div class=\"sec-w\">\n    <div class=\"badge r\">Anma Günleri</div>\n    <h2 class=\"sec-title\">Çanakkale'yi Anıyoruz</h2>\n    <div class=\"g2\">\n      <div class=\"anma-card\">\n        <div class=\"anma-date\"><div class=\"anma-day\">18</div><div class=\"anma-month\">Mart</div></div>\n        <div class=\"anma-body\">\n          <h4>Çanakkale Deniz Zaferi &amp; Şehitler Günü</h4>\n          <p>18 Mart 1915'te Türk topçusunun İtilaf filosunu bozguna uğrattığı günün yıldönümü. Tüm yurtta törenler, anma etkinlikleri ve resmi geçit yapılır. Şehitler için dualar edilir.</p>\n        </div>\n      </div>\n      <div class=\"anma-card\">\n        <div class=\"anma-date\"><div class=\"anma-day\">25</div><div class=\"anma-month\">Nisan</div></div>\n        <div class=\"anma-body\">\n          <h4>Çanakkale Kara Muharebesi Anma Günü</h4>\n          <p>ANZAC kuvvetlerinin Arıburnu'na çıkarma yaptığı gün. Türkiye'de ve ANZAC ülkelerinde (Avustralya, Yeni Zelanda) törenlerle anılır. Gelibolu'daki Şehitler Abidesi'nde devlet törenleri düzenlenir.</p>\n        </div>\n      </div>\n      <div class=\"anma-card\">\n        <div class=\"anma-date\" style=\"background:var(--dk2)\"><div class=\"anma-day\">6/9</div><div class=\"anma-month\">Ağustos</div></div>\n        <div class=\"anma-body\">\n          <h4>Anafartalar Muharebesi Anma Günü</h4>\n          <p>6-10 Ağustos 1915 tarihlerinde gerçekleşen Anafartalar Muharebesi'nin yıldönümü. Mustafa Kemal'in Anafartalar Grubu komutanı olarak kazandığı zafer anılır.</p>\n        </div>\n      </div>\n      <div class=\"anma-card\">\n        <div class=\"anma-date\" style=\"background:#6b7280\"><div class=\"anma-day\">9</div><div class=\"anma-month\">Ocak</div></div>\n        <div class=\"anma-body\">\n          <h4>Tahliye ve Zafer'in Tescili</h4>\n          <p>9 Ocak 1916'da son İtilaf kuvvetleri Gelibolu'yu terk etti. Bu tarih, sekiz aylık savunmanın resmen sona erdiği ve Türk zaferinin kesinleştiği gün olarak tarihe geçmiştir.</p>\n        </div>\n      </div>\n    </div>\n  </div>\n</div>\n\n\n<div class=\"cta-band\">\n  <div class=\"cta-w\">\n    <div class=\"cta-text\">\n      <h3>Çanakkale Ruhunu Yaşatıyoruz</h3>\n      <p>Şehitlerimizi saygıyla anıyor, bu toprakların bedelini asla unutmuyoruz.</p>\n    </div>\n    <div style=\"display:flex;gap:10px;flex-wrap:wrap\">\n      <a href=\"/kurtulus-savasi\" class=\"btn-wh\">⚔️ Kurtuluş Savaşı</a>\n      <a href=\"/milli-gunler\" class=\"btn-ol\">📅 Millî Günler</a>\n    </div>\n  </div>\n</div>\n\n</div>\n</div>","enabled":true,"fullWidth":false,"importSource":"wordpress-template","sourceName":"page-canakkale-savasi.php","importedAt":"2026-05-22T18:04:21.010Z"}]}